sambristol_ssabp_w/__init__.py
sambristol_ssabp_w/correlationintegrands.py
sambristol_ssabp_w/effectivepotential.py
sambristol_ssabp_w/mayerint.py
sambristol_ssabp_w/meshode.py
sambristol_ssabp_w/trimerbc.py
sambristol_ssabp_w/wbessel.py
sambristol_ssabp_w/wdiffpot.py
sambristol_ssabp_w/whardsphere.py
sambristol_ssabp_w/wlowDt.py
sambristol_ssabp_w/wperturb.py
sambristol_ssabp_w/wxi.py
sambristol_ssabp_w-0.0.15.dist-info/LICENSE
sambristol_ssabp_w-0.0.15.dist-info/METADATA
sambristol_ssabp_w-0.0.15.dist-info/WHEEL
sambristol_ssabp_w-0.0.15.dist-info/top_level.txt
sambristol_ssabp_w-0.0.15.dist-info/RECORD
