Metadata-Version: 2.1
Name: sambristol-ssabp-w
Version: 0.0.15
Summary: package to compute ODE's and statmech relevant to active brownian particle steady states
Home-page: https://github.com/samueljmcameron/sambristol_ssabp_w
Author: Sam Cameron
Author-email: samuel.j.m.cameron@gmail.com
Classifier: Programming Language :: Python :: 3
Classifier: License :: OSI Approved :: GNU General Public License v3 (GPLv3)
Classifier: Operating System :: OS Independent
Requires-Python: >=3.3
License-File: LICENSE
Requires-Dist: scipy
Requires-Dist: numpy
Requires-Dist: samspecialfuncs (>=0.0.15)
